packagecake/__init__.py
packagecake/__main__.py
packagecake/bakery.py
packagecake/pypi_cake_stats.py
packagecake-1.0.2.dist-info/LICENSE
packagecake-1.0.2.dist-info/METADATA
packagecake-1.0.2.dist-info/WHEEL
packagecake-1.0.2.dist-info/top_level.txt
packagecake-1.0.2.dist-info/RECORD
