Metadata-Version: 2.1
Name: packagecake
Version: 1.0.2
Summary: Turn your Python package into a delicious cake
Home-page: https://github.com/sirfuzzalot/packagecake/
Author: Tom Saunders
License: MIT
Project-URL: Tracker, https://github.com/sirfuzzalot/packagecake/issues
Project-URL: Documentation, https://github.com/sirfuzzalot/packagecake/blob/main/README.md
Project-URL: Source, https://github.com/sirfuzzalot/packagecake/
Platform: UNKNOWN
Classifier: Development Status :: 3 - Alpha
Classifier: Intended Audience :: Developers
Classifier: License :: OSI Approved :: MIT License
Classifier: Programming Language :: Python
Classifier: Programming Language :: Python :: 3
Classifier: Programming Language :: Python :: 3 :: Only
Classifier: Programming Language :: Python :: 3.8
Classifier: Programming Language :: Python :: 3.9
Classifier: Operating System :: OS Independent
Classifier: Topic :: Utilities
Requires-Python: >=3.8
License-File: LICENSE
Requires-Dist: requests (>=2)
